fast_downloader/__init__.py
fast_downloader/settings.py
fast_downloader/downloaders/__init__.py
fast_downloader/downloaders/async_download_file.py
fast_downloader/downloaders/constants.py
fast_downloader/downloaders/download_file.py
fast_downloader/utils/__init__.py
fast_downloader/utils/async_utils.py
fast_downloader/utils/constants.py
fast_downloader/utils/utils.py
fast_downloader-0.0.1.dist-info/LICENSE
fast_downloader-0.0.1.dist-info/METADATA
fast_downloader-0.0.1.dist-info/WHEEL
fast_downloader-0.0.1.dist-info/top_level.txt
fast_downloader-0.0.1.dist-info/RECORD
