Metadata-Version: 2.1
Name: fast-downloader
Version: 0.0.1
Summary: The package shares fast download api
Home-page: https://github.com/itamarf84/fast_downloader
Author: Itamar Farchy
Author-email: itamar.farchy@email.com
License: LICENSE
Platform: UNKNOWN
Classifier: License :: OSI Approved :: Apache Software License
Classifier: Programming Language :: Python
Classifier: Programming Language :: Python :: 3
Classifier: Programming Language :: Python :: 3.6
Classifier: Programming Language :: Python :: 3.7
Classifier: Programming Language :: Python :: 3.8
Classifier: Topic :: Internet :: WWW/HTTP
Classifier: Operating System :: OS Independent
Requires-Python: >=3.6
